__init__.py
main.py
parser.py
ticktracer-0.0.6.dist-info/LICENSE
ticktracer-0.0.6.dist-info/METADATA
ticktracer-0.0.6.dist-info/WHEEL
ticktracer-0.0.6.dist-info/entry_points.txt
ticktracer-0.0.6.dist-info/top_level.txt
ticktracer-0.0.6.dist-info/RECORD
