Metadata-Version: 2.1
Name: ticktracer
Version: 0.0.6
Summary: An all-in-one tool to assess the latency of crypto exchange APIs.
Author-email: Daniel Molenaars <daniel.molenaars@alibaba-inc.com>
License:                                  Apache License
Keywords: crypto,exchange,latency,tester
Requires-Python: >=3.9
License-File: LICENSE
Requires-Dist: aiohttp==3.10
Requires-Dist: ccxt==4.4.29
Requires-Dist: numpy
Requires-Dist: prettytable
Requires-Dist: pyshark
Requires-Dist: sslkeylog
Requires-Dist: tqdm
